boastlabs/__init__.py
boastlabs/functions/__init__.py
boastlabs/functions/dispatch/__init__.py
boastlabs/functions/dispatch/events.py
boastlabs/functions/dispatch/execution.py
boastlabs/functions/dispatch/worker.py
boastlabs/functions/execution/__init__.py
boastlabs/functions/execution/config.py
boastlabs/functions/execution/exceptions.py
boastlabs/functions/execution/execution.py
boastlabs/functions/execution/functions.py
boastlabs/functions/execution/progress.py
boastlabs/functions/execution/threading.py
boastlabs/functions/execution/time.py
boastlabs/functions/execution/worker.py
boastlabs/functions/execution/events/__init__.py
boastlabs/functions/execution/events/events.py
boastlabs/functions/execution/events/handler.py
boastlabs/functions/jobs/__init__.py
boastlabs/functions/jobs/events.py
boastlabs/functions/jobs/execution.py
boastlabs/functions/jobs/worker.py
boastlabs_cloud_functions-1.0.9.dist-info/METADATA
boastlabs_cloud_functions-1.0.9.dist-info/WHEEL
boastlabs_cloud_functions-1.0.9.dist-info/top_level.txt
boastlabs_cloud_functions-1.0.9.dist-info/RECORD
