Metadata-Version: 2.1
Name: boastlabs-cloud-functions
Version: 1.0.9
Summary: Boastlabs cloud function template
Home-page: https://github.com/musatdragosro/boastlabs-cloud-functions
Author: Musat Dragos
Author-email: musat.dragos.ro@gmail.com
License: MIT
Platform: UNKNOWN
Classifier: License :: OSI Approved :: MIT License
Classifier: Programming Language :: Python :: 3
Classifier: Programming Language :: Python :: 3.7
Requires-Dist: firebase-admin
Requires-Dist: semantic-version
